svg/__init__.py
svg/_filters.py
svg/_helpers.py
svg/_mixins.py
svg/_path.py
svg/_transforms.py
svg/_types.py
svg/elements.py
svg/py.typed
svg_py-1.9.2.dist-info/LICENSE
svg_py-1.9.2.dist-info/WHEEL
svg_py-1.9.2.dist-info/METADATA
svg_py-1.9.2.dist-info/RECORD
