Metadata-Version: 2.1
Name: svg.py
Version: 1.9.2
Summary: SVG drawing library
Home-page: https://github.com/orsinium-labs/svg
License: MIT
Keywords: svg,drawing,vector
Author: Gram
Author-email: gram@orsinium.dev
Requires-Python: >=3.7
Classifier: Development Status :: 5 - Production/Stable
Classifier: Intended Audience :: Developers
Classifier: License :: OSI Approved :: MIT License
Classifier: Programming Language :: Python
Classifier: Topic :: Software Development
Requires-Dist: isort ; extra == "dev"
Requires-Dist: mypy ; extra == "dev"
Requires-Dist: pytest ; extra == "dev"
Provides-Extra: dev
